mosync.py
mosync-0.1.0.dist-info/METADATA
mosync-0.1.0.dist-info/WHEEL
mosync-0.1.0.dist-info/licenses/LICENSE
mosync-0.1.0.dist-info/RECORD
